setup.py
client/__init__.py
client/client.py
client/client/__init__.py
client/client/add_contact.py
client/client/database.py
client/client/del_contact.py
client/client/main_window.py
client/client/main_window_conv.py
client/client/start_dialog.py
client/client/transport.py
client/common/__init__.py
client/common/deccor_log.py
client/common/descryptors.py
client/common/errors.py
client/common/metaclasses.py
client/common/settings.py
client/common/utils.py
client/log/__init__.py
client/log/client_log_conf.py
client/log/server_log_conf.py
client/log/logs/__init__.py
client/unit_test/__init__.py
client/unit_test/test_client.py
client/unit_test/test_server.py
client/unit_test/test_utils.py
mess_client_leget.egg-info/PKG-INFO
mess_client_leget.egg-info/SOURCES.txt
mess_client_leget.egg-info/dependency_links.txt
mess_client_leget.egg-info/requires.txt
mess_client_leget.egg-info/top_level.txt