Metadata-Version: 1.0
Name: mess-client-leget
Version: 0.0.1
Summary: mess_client
Home-page: UNKNOWN
Author: Dmitriy Lobanov
Author-email: lobanov.leget@yandex.ru
License: UNKNOWN
Platform: UNKNOWN
